pygamemadeeasy/__init__.py
pygamemadeeasy/colors.py
pygamemadeeasy/keys.py
pygamemadeeasy-2019.2.11.dist-info/LICENSE.txt
pygamemadeeasy-2019.2.11.dist-info/METADATA
pygamemadeeasy-2019.2.11.dist-info/WHEEL
pygamemadeeasy-2019.2.11.dist-info/top_level.txt
pygamemadeeasy-2019.2.11.dist-info/RECORD
