Metadata-Version: 2.1
Name: pygamemadeeasy
Version: 2019.2.11
Summary: A module intended to abstract away some of the complexity of using PyGame for beginner programmers.
Home-page: https://pbaumgarten.com/pygamemadeeasy
Author: Paul Baumgarten
Author-email: pbaumgarten@gmail.com
License: UNKNOWN
Keywords: python pygame beginner
Platform: UNKNOWN
Classifier: Programming Language :: Python :: 3
Classifier: License :: OSI Approved :: MIT License
Classifier: Operating System :: OS Independent
Requires-Python: >=3
Requires-Dist: pygame
